Metadata-Version: 1.0
Name: detache
Version: 0.2.3
Summary: A simple, intuitive Discord bot framework for Python
Home-page: http://github.com/reshanie/detache
Author: J Patrick Dill
Author-email: jamespatrickdill@gmail.com
License: MIT
Platform: UNKNOWN
